arcane/google_analytics/__init__.py
arcane/google_analytics/client.py
arcane/google_analytics/exceptions.py
arcane/google_analytics/lib.py
arcane_google_analytics-1.1.15.dist-info/METADATA
arcane_google_analytics-1.1.15.dist-info/WHEEL
arcane_google_analytics-1.1.15.dist-info/RECORD
