Metadata-Version: 2.1
Name: arcane-google-analytics
Version: 1.1.15
Summary: A package to use Google Analytics API
Author: Arcane
Author-email: product@arcane.run
Requires-Python: >=3.9,<3.12
Classifier: Programming Language :: Python :: 3
Classifier: Programming Language :: Python :: 3.9
Classifier: Programming Language :: Python :: 3.10
Classifier: Programming Language :: Python :: 3.11
Requires-Dist: arcane-core (>=1,<2)
Requires-Dist: arcane-credentials (>=0.1,<0.2)
Requires-Dist: arcane-datastore (>=1,<2)
Requires-Dist: arcane-requests (>=0,<1)
Requires-Dist: google-api-python-client (>=2.149.0)
